[
    {
        "url": "https://jacobstreams.com/",
        "icon": "/assets/images/projects/jacobstreams.png",
        "name": "jacobstreams.com",
        "desc": "The official website for JacobStreams, showcasing his socials, events and more.",
        "tech": [
            {
                "class": "vs-code", 
                "name": "VS Code"
            },
            {
                "class": "html", 
                "name": "HTML"
            },
            {
                "class": "css", 
                "name": "CSS"
            },
            {
                "class": "js", 
                "name": "JS"
            }
        ]
    },
    {
        "url": "https://soapmug.itch.io/I_SEE_YOU",
        "icon": "/assets/images/projects/i_see_you.png",
        "name": "I SEE YOU",
        "desc": "A game built in ~2 days by me and three other people for the D&A Game Jam and won Most Promising.",
        "tech": [
            {
                "class": "unity", 
                "name": "Unity"
            },
            {
                "class": "visual-studio", 
                "name": "Visual Studio"
            },
            {
                "class": "cs", 
                "name": "C#"
            }
        ]
    },
    {
        "url": "https://kadenissilly.com/",
        "icon": "/assets/images/me.png",
        "name": "kadenissilly.com",
        "desc": "My personal bio site, showcasing my social media.",
        "tech": [
            {
                "class": "vs-code", 
                "name": "VS Code"
            },
            {
                "class": "html", 
                "name": "HTML"
            },
            {
                "class": "css", 
                "name": "CSS"
            }
        ]
    },
    {
        "url": "https://github.com/KadenIsSilly/M-Day",
        "icon": "/assets/images/projects/m-day.png",
        "name": "M-Day",
        "desc": "A mod for the game Advanced Warfare that removes all the mutated zombies",
        "tech": [
            {
                "class": "vs-code", 
                "name": "VS Code"
            },
            {
                "class": "gsc", 
                "name": "GSC"
            }
        ]
    },
    {
        "url": "https://kaden-the.dev/",
        "icon": "/assets/images/me.png",
        "name": "kaden-the.dev",
        "desc": "My personal portfolio site, showcasing all my projects and the technologies I work with.",
        "tech": [
            {
                "class": "vs-code", 
                "name": "VS Code"
            },
            {
                "class": "html", 
                "name": "HTML"
            },
            {
                "class": "css", 
                "name": "CSS"
            },
            {
                "class": "js", 
                "name": "JS"
            }
        ]
    },
    {
        "url": "https://archivesmp.net/",
        "icon": "/assets/images/projects/archivesmp.png",
        "name": "archivesmp.net",
        "desc": "The official website for the ArchiveSMP. Showcasing all the members.",
        "tech": [
            {
                "class": "vs-code", 
                "name": "VS Code"
            },
            {
                "class": "html", 
                "name": "HTML"
            },
            {
                "class": "css", 
                "name": "CSS"
            },
            {
                "class": "js", 
                "name": "JS"
            }
        ]
    },
    {
        "url": "https://www.youtube.com/watch?v=xj8ZapKHgZY&t=1345s",
        "icon": "/assets/images/projects/ktvu.png",
        "name": "Keep the Viewers Up!",
        "desc": "A fast paced game made in ~28 hours for JacobStreams' Talent Show",
        "tech": [
            {
                "class": "unreal", 
                "name": "Unreal Engine"
            },
            {
                "class": "blueprint", 
                "name": "Blueprint"
            }
        ]
    },
    {
        "url": "https://www.roblox.com/games/13413041261/Coco_Pops",
        "icon": "/assets/images/projects/coco_pops.png",
        "name": "Coco Pops.",
        "desc": "A horror game about Coco Pops built in ~3 hours.",
        "tech": [
            {
                "class": "roblox", 
                "name": "Roblox Studio"
            },
            {
                "class": "lua", 
                "name": "Lua"
            }
        ]
    },
    {
        "url": "https://www.roblox.com/games/12651990651/Explode",
        "icon": "/assets/images/projects/explode.png",
        "name": "Explode.",
        "desc": "A game built in ~2 hours that does exactly what the name implies.",
        "tech": [
            {
                "class": "roblox", 
                "name": "Roblox Studio"
            },
            {
                "class": "lua", 
                "name": "Lua"
            }
        ]
    }
]